akithon/__init__.py
akithon/version.py
akithon/_client/__init__.py
akithon/_client/akinator.py
akithon/_client/constants.py
akithon/_client/functions.py
akithon/_client/session.py
akithon-0.1.1.dist-info/LICENSE
akithon-0.1.1.dist-info/METADATA
akithon-0.1.1.dist-info/WHEEL
akithon-0.1.1.dist-info/top_level.txt
akithon-0.1.1.dist-info/RECORD
